htsget/__init__.py
htsget/_version.py
htsget/cli.py
htsget/exceptions.py
htsget/io.py
htsget/protocol.py
htsget-0.2.6.dist-info/LICENSE
htsget-0.2.6.dist-info/METADATA
htsget-0.2.6.dist-info/WHEEL
htsget-0.2.6.dist-info/entry_points.txt
htsget-0.2.6.dist-info/top_level.txt
htsget-0.2.6.dist-info/RECORD
